user_tools/__init__.py
user_tools/version.py
user_tools/common/__init__.py
user_tools/common/ucheck.py
user_tools/common/ucmd.py
user_tools/common/uencoding.py
user_tools/common/uhash.py
user_tools/common/uobj.py
user_tools/common/ustr.py
user_tools/common/utime.py
user_tools/db/__init__.py
user_tools/db/umysql.py
user_tools/file/__init__.py
user_tools/file/ucompress.py
user_tools/file/ucsv.py
user_tools/file/uexcel.py
user_tools/file/ufile.py
user_tools/file/ujson.py
user_tools/file/ulog.py
user_tools/file/upath.py
user_tools/network/__init__.py
user_tools/network/uhttp.py
user_tools/network/unet.py
user_tools/network/ussh.py
user_tools-2.0.0.dist-info/METADATA
user_tools-2.0.0.dist-info/WHEEL
user_tools-2.0.0.dist-info/licenses/LICENSE
user_tools-2.0.0.dist-info/RECORD
