Metadata-Version: 2.4
Name: user_tools
Version: 2.0.0
Summary: 常用 Python 组件
Project-URL: Homepage, https://github.com/Skypekey/user_toolsv2/
Project-URL: Repository, https://github.com/Skypekey/user_toolsv2.git
Project-URL: Changelog, https://github.com/Skypekey/user_toolsv2/Changelog.md
Project-URL: Tracker, https://github.com/Skypekey/user_toolsv2/issues
Author-email: SkypeKey <enablekey@outlook.com>
License-File: LICENSE
Classifier: Development Status :: 5 - Production/Stable
Classifier: Intended Audience :: Developers
Classifier: License :: OSI Approved :: GNU Lesser General Public License v3 or later (LGPLv3+)
Classifier: Operating System :: MacOS :: MacOS X
Classifier: Operating System :: Microsoft :: Windows
Classifier: Operating System :: POSIX
Classifier: Programming Language :: Python :: 3 :: Only
Classifier: Programming Language :: Python :: 3.8
Classifier: Programming Language :: Python :: 3.9
Classifier: Programming Language :: Python :: 3.10
Classifier: Programming Language :: Python :: 3.11
Classifier: Programming Language :: Python :: 3.12
Classifier: Topic :: Software Development :: Build Tools
Requires-Python: >=3.8
Requires-Dist: pydantic>=2.11.7
Provides-Extra: all
Requires-Dist: chinesecalendar>=1.9.1; extra == 'all'
Requires-Dist: filetype>=1.2.0; extra == 'all'
Requires-Dist: openpyxl>=3.1.3; extra == 'all'
Requires-Dist: paramiko>=3.4.0; extra == 'all'
Requires-Dist: py7zr>=0.21.0; extra == 'all'
Requires-Dist: pymysql>=1.1.1; extra == 'all'
Requires-Dist: rarfile>=4.2; extra == 'all'
Requires-Dist: requests>=2.32.3; extra == 'all'
Provides-Extra: db
Requires-Dist: pymysql>=1.1.1; extra == 'db'
Provides-Extra: file
Requires-Dist: chinesecalendar>=1.9.1; extra == 'file'
Requires-Dist: filetype>=1.2.0; extra == 'file'
Requires-Dist: openpyxl>=3.1.3; extra == 'file'
Provides-Extra: net
Requires-Dist: paramiko>=3.4.0; extra == 'net'
Requires-Dist: requests>=2.32.3; extra == 'net'
Provides-Extra: tar
Requires-Dist: py7zr>=0.21.0; extra == 'tar'
Requires-Dist: rarfile>=4.2; extra == 'tar'
